flake8_pyprojecttoml/__init__.py
flake8_pyprojecttoml/py.typed
flake8_pyprojecttoml-0.0.2.dist-info/LICENSE.txt
flake8_pyprojecttoml-0.0.2.dist-info/METADATA
flake8_pyprojecttoml-0.0.2.dist-info/WHEEL
flake8_pyprojecttoml-0.0.2.dist-info/entry_points.txt
flake8_pyprojecttoml-0.0.2.dist-info/top_level.txt
flake8_pyprojecttoml-0.0.2.dist-info/RECORD
