Metadata-Version: 2.1
Name: flake8-pyprojecttoml
Version: 0.0.2
Summary: Inject pyproject.toml support into flake8.
Home-page: https://gitlab.com/durko/flake8-pyprojecttoml
Author: Marko Durkovic
Author-email: marko@miding.de
License: Apache 2.0
Project-URL: Code, https://gitlab.com/durko/flake8-pyprojecttoml
Project-URL: Documentation, https://durko.gitlab.io/flake8-pyprojecttoml
Project-URL: Issue tracker, https://gitlab.com/durko/flake8-pyprojecttoml/issues
Keywords: configuration,flake8,pyproject.toml
Platform: any
Classifier: Development Status :: 4 - Beta
Classifier: License :: OSI Approved :: Apache Software License
Classifier: Programming Language :: Python
Classifier: Programming Language :: Python :: 3 :: Only
Classifier: Programming Language :: Python :: 3.7
Classifier: Programming Language :: Python :: 3.8
Classifier: Programming Language :: Python :: 3.9
Classifier: Programming Language :: Python :: 3.10
Classifier: Topic :: Software Development :: Quality Assurance
Classifier: Typing :: Typed
Requires-Python: >=3.7
License-File: LICENSE.txt
Requires-Dist: flake8
Requires-Dist: tomli ; python_version < "3.11"
Provides-Extra: dev
Requires-Dist: darglint ; extra == 'dev'
Requires-Dist: flake8 ; extra == 'dev'
Requires-Dist: flake8-annotations ; extra == 'dev'
Requires-Dist: flake8-bugbear ; extra == 'dev'
Requires-Dist: flake8-commas ; extra == 'dev'
Requires-Dist: flake8-comprehensions ; extra == 'dev'
Requires-Dist: flake8-docstrings ; extra == 'dev'
Requires-Dist: flake8-fixme ; extra == 'dev'
Requires-Dist: flake8-isort ; extra == 'dev'
Requires-Dist: flake8-mutable ; extra == 'dev'
Requires-Dist: flake8-print ; extra == 'dev'
Requires-Dist: flake8-pytest-style ; extra == 'dev'
Requires-Dist: flake8-quotes ; extra == 'dev'
Requires-Dist: flake8-return ; extra == 'dev'
Requires-Dist: flake8-simplify ; extra == 'dev'
Requires-Dist: flake8-type-checking ; extra == 'dev'
Requires-Dist: flake8-use-fstring ; extra == 'dev'
Requires-Dist: mypy ; extra == 'dev'
Requires-Dist: pep8-naming ; extra == 'dev'
Requires-Dist: pylint ; extra == 'dev'
Requires-Dist: pytest ; extra == 'dev'
Requires-Dist: pytest-cov ; extra == 'dev'
Requires-Dist: toml ; extra == 'dev'
Requires-Dist: yapf ; extra == 'dev'
